{
    "pw": "9834876dcfb05cb167a5c24953eba58c4ac89b1adf57f28f2f9d09af107ee8f0",
    "tasks": {
        "07c83e0c-5abe-4cd7-936e-27583d973223": {
            "name": "aaa",
            "description": "eee",
            "status": "ready",
            "timeLimit": "2024/01/25 17:39:00"
        },
        "7092c9c2-ccc1-4a25-a00d-e791212738a5": {
            "name": "eee",
            "description": "www",
            "status": "not ready",
            "timeLimit": "2024/01/25 19:58:00"
        }
    }
}